pyawx/__init__.py
pyawx/actions.py
pyawx/api.py
pyawx/exceptions/__init__.py
pyawx/models/__init__.py
pyawx/models/_mixins.py
pyawx/models/adhoc.py
pyawx/models/applications.py
pyawx/models/credentials.py
pyawx/models/instances.py
pyawx/models/inventories.py
pyawx/models/jobs.py
pyawx/models/labels.py
pyawx/models/mixins.py
pyawx/models/notifications.py
pyawx/models/organizations.py
pyawx/models/projects.py
pyawx/models/types.py
pyawx/models/unified.py
pyawx/models/users.py
pyawx/models/workflows.py
pyawx_client-0.2.0.dist-info/LICENSE.txt
pyawx_client-0.2.0.dist-info/METADATA
pyawx_client-0.2.0.dist-info/WHEEL
pyawx_client-0.2.0.dist-info/top_level.txt
pyawx_client-0.2.0.dist-info/RECORD
