Metadata-Version: 2.1
Name: pyawx-client
Version: 0.2.0
Summary: Python API to access Ansible AWX/Tower v2 API
Home-page: https://github.com/irunasroot/pyawx-client
Author: Dennis Whitney
Author-email: dennis@irunasroot.com
License: Apache 2.0
Download-URL: https://github.com/irunasroot/pyawx-client/archive/v0.2.0.tar.gz
Keywords: ansible,tower,awx,redhat,ansible tower,ansible awx,playbook,automation
Platform: UNKNOWN
Classifier: Development Status :: 3 - Alpha
Classifier: Intended Audience :: Developers
Classifier: Topic :: Software Development :: Build Tools
Classifier: License :: OSI Approved :: Apache Software License
Classifier: Programming Language :: Python :: 3.6
Classifier: Programming Language :: Python :: 3.7
Classifier: Programming Language :: Python :: 3.8
Classifier: Programming Language :: Python :: 3.9
Requires-Dist: requests
